reactive_reference/__init__.py
reactive_reference/docs/_build/doctrees/environment.pickle
reactive_reference/docs/_build/doctrees/event.doctree
reactive_reference/docs/_build/doctrees/index.doctree
reactive_reference/docs/_build/doctrees/modules.doctree
reactive_reference/docs/_build/doctrees/reference.doctree
reactive_reference/docs/_build/html/.buildinfo
reactive_reference/docs/_build/html/.nojekyll
reactive_reference/docs/_build/html/_sources/event.rst.txt
reactive_reference/docs/_build/html/_sources/index.rst.txt
reactive_reference/docs/_build/html/_sources/modules.rst.txt
reactive_reference/docs/_build/html/_sources/reference.rst.txt
reactive_reference/docs/_build/html/_static/alabaster.css
reactive_reference/docs/_build/html/_static/basic.css
reactive_reference/docs/_build/html/_static/custom.css
reactive_reference/docs/_build/html/_static/doctools.js
reactive_reference/docs/_build/html/_static/documentation_options.js
reactive_reference/docs/_build/html/_static/file.png
reactive_reference/docs/_build/html/_static/language_data.js
reactive_reference/docs/_build/html/_static/minus.png
reactive_reference/docs/_build/html/_static/plus.png
reactive_reference/docs/_build/html/_static/pygments.css
reactive_reference/docs/_build/html/_static/searchtools.js
reactive_reference/docs/_build/html/_static/sphinx_highlight.js
reactive_reference/docs/_build/html/event.html
reactive_reference/docs/_build/html/genindex.html
reactive_reference/docs/_build/html/index.html
reactive_reference/docs/_build/html/modules.html
reactive_reference/docs/_build/html/objects.inv
reactive_reference/docs/_build/html/py-modindex.html
reactive_reference/docs/_build/html/reference.html
reactive_reference/docs/_build/html/search.html
reactive_reference/docs/_build/html/searchindex.js
reactive_reference/docs/conf.py
reactive_reference/docs/event.rst
reactive_reference/docs/index.rst
reactive_reference/docs/make.bat
reactive_reference/docs/Makefile
reactive_reference/docs/modules.rst
reactive_reference-0.2.0.dist-info/METADATA
reactive_reference-0.2.0.dist-info/WHEEL
reactive_reference-0.2.0.dist-info/RECORD
