Metadata-Version: 2.1
Name: reactive-reference
Version: 0.2.0
Summary: A collection of mini projects for a reactive programming approach
Author: Carlos Silva
Author-email: carlos.miguel.silva@protonmail.com
Requires-Python: >=3.10,<4.0
Classifier: Programming Language :: Python :: 3
Classifier: Programming Language :: Python :: 3.10
Classifier: Programming Language :: Python :: 3.11
Classifier: Programming Language :: Python :: 3.12
Requires-Dist: pre-commit (>=3.6.0,<4.0.0)
